{
  "items": [
    {
      "environments": [
        {
          "name": "production",
          "id": "d6e523e17e1d929e6277292aea28b903"
        }
      ],
      "item": {
        "notes": "",
        "data": []
      }
    },
    {
      "environments": [
        {
          "name": "production",
          "id": "538b731c16026f131aa0b314def63f9b"
        }
      ],
      "item": {
        "notes": "",
        "data": []
      }
    },
    {
      "environments": [
        {
          "name": "production",
          "id": "549b5522072c32f00946aa2ea073bfbd"
        }
      ],
      "item": {
        "notes": "",
        "data": {
          "table": []
        }
      }
    },
    {
      "environments": [
        {
          "name": "production",
          "id": "81caa0242fa168d128995977cd4026a8"
        }
      ],
      "item": {
        "notes": "",
        "data": []
      }
    },
    {
      "environments": [
        {
          "name": "production",
          "id": "81caa0242fa168d128995977cd45268b"
        }
      ],
      "item": {
        "notes": "",
        "data": {
          "table": []
        }
      }
    },
    {
      "environments": [
        {
          "name": "production",
          "id": "beb6de8405dcbea50a354dc453822c18"
        }
      ],
      "item": {
        "notes": "",
        "data": []
      }
    }
  ]
}